{
    "configurations": [
        {
            "name": "RmlUi-Test-x64-Debug",
            "generator": "Ninja",
            "configurationType": "Debug",
            "inheritEnvironments": [ "msvc_x64_x64" ],
            "buildRoot": "${projectDir}\\_Build\\${configurationType}",
            "installRoot": "${projectDir}\\build.out\\install\\${name}",
            "codeAnalysisRuleset": "${projectDir}\\CODEANALYSIS.ruleset",
            "cmakeCommandArgs": "",
            "buildCommandArgs": "-v",
            "ctestCommandArgs": "",
            "variables": []
        },
        {
            "name": "RmlUi-Test-x64-Release",
            "generator": "Ninja",
            "configurationType": "Release",
            "inheritEnvironments": [ "msvc_x64_x64" ],
            "buildRoot": "${projectDir}\\_Build\\${configurationType}",
            "installRoot": "${projectDir}\\build.out\\install\\${name}",
            "codeAnalysisRuleset": "${projectDir}\\CODEANALYSIS.ruleset",
            "cmakeCommandArgs": "",
            "buildCommandArgs": "-v",
            "ctestCommandArgs": "",
            "variables": []
        }
    ]
}
